{
  "source": {
    "file_name": "Gjennomfoeringsplan (1).pdf",
    "relative_path": "Gjennomfoeringsplan (1).pdf",
    "size_bytes": 203723,
    "modified_time": "2026-01-26T18:49:09.740520+00:00",
    "sha256": "5ea96b10ce90afc455bfbfd808c539179099864ca8a03963d629c87cce5d1f90"
  },
  "pdfinfo": {
    "Author": "",
    "Creator": "EO.Pdf",
    "Producer": "Sikri AS,  PixToolsLib Version 2.10.8.9",
    "CreationDate": "Thu Oct 10 15:35:36 2024 CEST",
    "ModDate": "Thu Oct 10 15:35:36 2024 CEST",
    "Custom Metadata": "no",
    "Metadata Stream": "yes",
    "Tagged": "yes",
    "UserProperties": "no",
    "Suspects": "no",
    "Form": "none",
    "JavaScript": "no",
    "Pages": "4",
    "Encrypted": "no",
    "Page size": "842 x 596 pts (A4)",
    "Page rot": "0",
    "File size": "203723 bytes",
    "Optimized": "no",
    "PDF version": "1.7"
  },
  "extraction": {
    "tool": "pdftotext",
    "options": "-layout",
    "extracted_at": "2026-01-26T19:16:02.982853+00:00",
    "page_count": 4,
    "has_text": true
  },
  "pages": [
    {
      "page_number": 1,
      "text": "                                                                                                                                09.10.2024 14:39:50 AR637492594\n                                  Gjennomføringsplan\n\n                                  Kommunens saksnummer (år, sekvensnummer):             2024 53701\n\n                                  Versjonsnr.:           2\n                                  Prosjektnavn:          Skøyen terrasse 1\n\n\n                                  Eiendom/Byggested\n\n                                  Gnr                                             Bnr                Festenr   Seksjonsnr\n                                  3                                               493                0         0\n\n\n                                  Kommune         Oslo\n\n                                  Adresse         Skøyen terrasse 1 , 0276 Oslo\n09.10.2024 14:39:50 AR637492594\n\n\n\n\n                                                                                                                            1\n",
      "char_count": 1038,
      "line_count": 25
    },
    {
      "page_number": 2,
      "text": "                                  Oversikt over ansvarsfordeling\n\n\n\n\n                                                                                                                                                                                                     09.10.2024 14:39:50 AR637492594\n                                  ANSVARLIG PROSJEKTERENDE\n                                                                                                       Tiltaks-    Foretakets org nummer og   Planlagt samsvars/kontrollerklæring,     Ansvar\n                                  Funksjon    Beskrivelse av ansvarsområdet\n                                                                                                       klasse      navn                       dato (vises når erklæringen er avgi )   avslu et\n\n                                  PRO         Arkitektur kny et l ombygningen ved kontorer i 1. etg.       1       881894742                  Rammesøknad, 08.03.2024\n                                                                                                                   WSP NORGE AS\n                                  PRO         Brannkonsept (Tiltak: Utbedring bærende                      1       881894742                  Rammesøknad, 29.02.2024\n                                              konstruksjoner)                                                      WSP NORGE AS\n                                  PRO         Geoteknikk                                                   2       925362441                  Rammesøknad, 29.02.2024\n                                                                                                                   GRUNNTEKNIKK AS\n                                  PRO         Konstruksjonssikkerhet                                       2       881894742                  Rammesøknad, 29.02.2024\n                                                                                                                   WSP NORGE AS               E rinns-/igangse ngssøknad,\n                                                                                                                                              09.10.2024\n                                  PRO         Sanitærinstallasjoner                                        2       881894742                  Rammesøknad, 14.03.2024\n                                                                                                                   WSP NORGE AS\n                                  PRO         Slukkeinstallasjoner                                         2       881894742                  Rammesøknad, 14.03.2024\n                                                                                                                   WSP NORGE AS\n\n                                  ANSVARLIG UTFØRENDE\n                                                                                                       Tiltaks-   Foretakets org nummer og    Planlagt samsvars/kontrollerklæring,     Ansvar\n                                  Funksjon    Beskrivelse av ansvarsområdet\n                                                                                                       klasse     navn                        dato (vises når erklæringen er avgi )   avslu et\n09.10.2024 14:39:50 AR637492594\n\n\n\n\n                                  UTF         Montering av bærende metall- eller                           2      996414507                   Ferdiga est\n                                              betongkonstruksjoner                                                SKAPE ENTREPRENØR AS\n                                  UTF         Plasstøpte betongkonstruksjoner                              2      996414507                   Ferdiga est\n                                                                                                                  SKAPE ENTREPRENØR AS\n                                  UTF         Sanitærinstallasjoner_UTF                                    2      987150440                   Ferdiga est\n                                                                                                                  K/S RØR AS\n                                  UTF         Slukkeinstallasjoner_UTF                                     2      987150440                   Ferdiga est\n                                                                                                                  K/S RØR AS\n\n\n                                                                                                                                                                                                 2\n",
      "char_count": 4658,
      "line_count": 46
    },
    {
      "page_number": 3,
      "text": "                                  ANSVARLIG KONTROLLERENDE\n                                                                                                            Tiltaks-   Foretakets org nummer og     Planlagt samsvars/kontrollerklæring,     Ansvar\n\n\n\n\n                                                                                                                                                                                                           09.10.2024 14:39:50 AR637492594\n                                  Funksjon        Beskrivelse av ansvarsområdet\n                                                                                                            klasse     navn                         dato (vises når erklæringen er avgi )   avslu et\n\n                                  KONTROLL        Geoteknikk (i ltaksklasse 2 og 3)                             2      997325230                    Ferdiga est\n                                                                                                                       VSO CONSULTING AS\n                                  KONTROLL        Konstruksjonssikkerhet (i ltaksklasse 2 og 3)                 2      997325230                    Ferdiga est\n                                                                                                                       VSO CONSULTING AS\n\n\n                                  Ansvarlig søker\n\n                                  Navn                        WSP Norge AS\n\n                                  Organisasjonsnummer         881894742\n\n                                  Tiltaksklasse               2\n\n\n\n\n                                  Signert av\n                                   MARTHE DISEN på vegne av WSP NORGE AS\n\n                                                                                       De e dokumentet er signert elektronisk og arkivert i Al nn\n09.10.2024 14:39:50 AR637492594\n\n\n\n\n                                                                                                                                                                                                       3\n",
      "char_count": 2138,
      "line_count": 38
    },
    {
      "page_number": 4,
      "text": "Filvedlegg:\n Ansvarsrett KS Rør.pdf\n Skøyen Terrasse Erklæring om ansvar PRO Geo.pdf\n 240930-Skøyen-terrasse-erklarin-om-ansv-RIB-RIG-Kontroll.pdf\n Ansvarsrett Skape.pdf\n Vi innvilger søknaden om samtykke etter automatisk saksbehandling (2).pdf\n",
      "char_count": 245,
      "line_count": 7
    }
  ],
  "text": "                                                                                                                                09.10.2024 14:39:50 AR637492594\n                                  Gjennomføringsplan\n\n                                  Kommunens saksnummer (år, sekvensnummer):             2024 53701\n\n                                  Versjonsnr.:           2\n                                  Prosjektnavn:          Skøyen terrasse 1\n\n\n                                  Eiendom/Byggested\n\n                                  Gnr                                             Bnr                Festenr   Seksjonsnr\n                                  3                                               493                0         0\n\n\n                                  Kommune         Oslo\n\n                                  Adresse         Skøyen terrasse 1 , 0276 Oslo\n09.10.2024 14:39:50 AR637492594\n\n\n\n\n                                                                                                                            1\n\f                                  Oversikt over ansvarsfordeling\n\n\n\n\n                                                                                                                                                                                                     09.10.2024 14:39:50 AR637492594\n                                  ANSVARLIG PROSJEKTERENDE\n                                                                                                       Tiltaks-    Foretakets org nummer og   Planlagt samsvars/kontrollerklæring,     Ansvar\n                                  Funksjon    Beskrivelse av ansvarsområdet\n                                                                                                       klasse      navn                       dato (vises når erklæringen er avgi )   avslu et\n\n                                  PRO         Arkitektur kny et l ombygningen ved kontorer i 1. etg.       1       881894742                  Rammesøknad, 08.03.2024\n                                                                                                                   WSP NORGE AS\n                                  PRO         Brannkonsept (Tiltak: Utbedring bærende                      1       881894742                  Rammesøknad, 29.02.2024\n                                              konstruksjoner)                                                      WSP NORGE AS\n                                  PRO         Geoteknikk                                                   2       925362441                  Rammesøknad, 29.02.2024\n                                                                                                                   GRUNNTEKNIKK AS\n                                  PRO         Konstruksjonssikkerhet                                       2       881894742                  Rammesøknad, 29.02.2024\n                                                                                                                   WSP NORGE AS               E rinns-/igangse ngssøknad,\n                                                                                                                                              09.10.2024\n                                  PRO         Sanitærinstallasjoner                                        2       881894742                  Rammesøknad, 14.03.2024\n                                                                                                                   WSP NORGE AS\n                                  PRO         Slukkeinstallasjoner                                         2       881894742                  Rammesøknad, 14.03.2024\n                                                                                                                   WSP NORGE AS\n\n                                  ANSVARLIG UTFØRENDE\n                                                                                                       Tiltaks-   Foretakets org nummer og    Planlagt samsvars/kontrollerklæring,     Ansvar\n                                  Funksjon    Beskrivelse av ansvarsområdet\n                                                                                                       klasse     navn                        dato (vises når erklæringen er avgi )   avslu et\n09.10.2024 14:39:50 AR637492594\n\n\n\n\n                                  UTF         Montering av bærende metall- eller                           2      996414507                   Ferdiga est\n                                              betongkonstruksjoner                                                SKAPE ENTREPRENØR AS\n                                  UTF         Plasstøpte betongkonstruksjoner                              2      996414507                   Ferdiga est\n                                                                                                                  SKAPE ENTREPRENØR AS\n                                  UTF         Sanitærinstallasjoner_UTF                                    2      987150440                   Ferdiga est\n                                                                                                                  K/S RØR AS\n                                  UTF         Slukkeinstallasjoner_UTF                                     2      987150440                   Ferdiga est\n                                                                                                                  K/S RØR AS\n\n\n                                                                                                                                                                                                 2\n\f                                  ANSVARLIG KONTROLLERENDE\n                                                                                                            Tiltaks-   Foretakets org nummer og     Planlagt samsvars/kontrollerklæring,     Ansvar\n\n\n\n\n                                                                                                                                                                                                           09.10.2024 14:39:50 AR637492594\n                                  Funksjon        Beskrivelse av ansvarsområdet\n                                                                                                            klasse     navn                         dato (vises når erklæringen er avgi )   avslu et\n\n                                  KONTROLL        Geoteknikk (i ltaksklasse 2 og 3)                             2      997325230                    Ferdiga est\n                                                                                                                       VSO CONSULTING AS\n                                  KONTROLL        Konstruksjonssikkerhet (i ltaksklasse 2 og 3)                 2      997325230                    Ferdiga est\n                                                                                                                       VSO CONSULTING AS\n\n\n                                  Ansvarlig søker\n\n                                  Navn                        WSP Norge AS\n\n                                  Organisasjonsnummer         881894742\n\n                                  Tiltaksklasse               2\n\n\n\n\n                                  Signert av\n                                   MARTHE DISEN på vegne av WSP NORGE AS\n\n                                                                                       De e dokumentet er signert elektronisk og arkivert i Al nn\n09.10.2024 14:39:50 AR637492594\n\n\n\n\n                                                                                                                                                                                                       3\n\fFilvedlegg:\n Ansvarsrett KS Rør.pdf\n Skøyen Terrasse Erklæring om ansvar PRO Geo.pdf\n 240930-Skøyen-terrasse-erklarin-om-ansv-RIB-RIG-Kontroll.pdf\n Ansvarsrett Skape.pdf\n Vi innvilger søknaden om samtykke etter automatisk saksbehandling (2).pdf\n\f"
}